py_uds_address-2.0.0.dist-info/licenses/LICENSE
uds_address/__init__.py
uds_address/ecu/__init__.py
uds_address/ecu/can/__init__.py
uds_address/ecu/can/obd2.py
uds_address/hyundai/__init__.py
uds_address/hyundai/i20/__init__.py
uds_address/hyundai/i20/year_2021/__init__.py
uds_address/hyundai/i20/year_2021/can_obd2.py
py_uds_address-2.0.0.dist-info/METADATA
py_uds_address-2.0.0.dist-info/WHEEL
py_uds_address-2.0.0.dist-info/top_level.txt
py_uds_address-2.0.0.dist-info/RECORD
