Metadata-Version: 2.4
Name: py-uds-address
Version: 2.0.0
Summary: Collection of UDS addresses for various ECUs.
Author-email: Maciej Dąbrowski <maciej.dabrowski@software-quality.pl>, UDS Package Development <uds-package-development@googlegroups.com>
Maintainer-email: Maciej Dąbrowski <maciej.dabrowski@software-quality.pl>, UDS Package Development <uds-package-development@googlegroups.com>
Project-URL: Homepage, https://github.com/mdabrowski1990/uds
Project-URL: User Documentation, https://uds.readthedocs.io
Project-URL: Repository, https://github.com/mdabrowski1990/uds-address
Project-URL: Issues Tracking System, https://github.com/mdabrowski1990/uds-address/issues
Project-URL: Releases and Changelogs, https://github.com/mdabrowski1990/uds-address/releases
Project-URL: PyPI, https://pypi.org/project/py-uds-address/
Project-URL: Code Download, https://github.com/mdabrowski1990/uds-address/archive/refs/heads/main.zip
Keywords: uds,unified-diagnostic-services,automotive,on-board-diagnostic,obd,obd2,vehicle-diagnostic,iso14229,iso-14229,iso15765,iso-15765,ECU,address
Classifier: Development Status :: 5 - Production/Stable
Classifier: Intended Audience :: Developers
Classifier: Intended Audience :: Education
Classifier: Intended Audience :: Information Technology
Classifier: Intended Audience :: Telecommunications Industry
Classifier: Natural Language :: English
Classifier: Operating System :: OS Independent
Classifier: Programming Language :: Python
Classifier: Programming Language :: Python :: 3
Classifier: Programming Language :: Python :: 3 :: Only
Classifier: Programming Language :: Python :: 3.9
Classifier: Programming Language :: Python :: 3.10
Classifier: Programming Language :: Python :: 3.11
Classifier: Programming Language :: Python :: 3.12
Classifier: Programming Language :: Python :: 3.13
Classifier: Topic :: Scientific/Engineering :: Interface Engine/Protocol Translator
Classifier: Topic :: Software Development :: Embedded Systems
Classifier: Topic :: System :: Monitoring
Classifier: Topic :: System :: Networking
Requires-Python: >=3.9
License-File: LICENSE
Requires-Dist: py-uds==2.0.0
Provides-Extra: static-code-analysis
Requires-Dist: prospector==1.17.3; extra == "static-code-analysis"
Requires-Dist: mypy==1.17.1; extra == "static-code-analysis"
Requires-Dist: vulture==2.14; extra == "static-code-analysis"
Requires-Dist: bandit==1.8.6; extra == "static-code-analysis"
Requires-Dist: pyroma==5.0; extra == "static-code-analysis"
Provides-Extra: dependency-scan
Requires-Dist: pip-audit==2.9.0; extra == "dependency-scan"
Provides-Extra: sorting-imports
Requires-Dist: isort==6.0.1; extra == "sorting-imports"
Dynamic: license-file
